<?xml version="1.0" encoding="iso-8859-1" ?>

<menu>
  <item>
    <path>civicrm/campaign/manage</path>
    <title>Manage Campaign</title>
    <page_callback>CRM_Campaign_Form_Campaign</page_callback>
    <access_arguments>administer Campaign</access_arguments>
  </item>
  <item>
    <path>civicrm/survey/manage</path>
    <title>Manage Survey</title>
    <page_callback>CRM_Campaign_Form_Survey</page_callback>
    <access_arguments>administer Campaign</access_arguments>
  </item>
  <item>
    <path>civicrm/survey/browse</path>
    <title>Survey</title>
    <page_callback>CRM_Campaign_Page_Survey</page_callback>
  </item>
  <item>
    <path>civicrm/campaign/browse</path>
    <title>Campaign</title>
    <page_callback>CRM_Campaign_Page_Campaign</page_callback>
  </item>
</menu>
